[
  {
    "term_cd": "B",
    "course_id": "2015-B-11111",
    "course_name": "Added by dept",
    "cross_listed_flag": null,
    "course_title_short": null,
    "dept_name": "STAT",
    "catalog_id": "111",
    "instruction_format": "LEC",
    "section_num": "001",
    "primary_secondary_cd": "P",
    "sis_id": null,
    "affiliations": "EMPLOYEE-TYPE-ACADEMIC,STUDENT-STATUS-EXPIRED",
    "first_name": "Donald",
    "last_name": "Trump",
    "email_address": "trump@berkeley.edu",
    "evaluate": null,
    "dept_form": null,
    "evaluation_type": null,
    "modular_course": "y",
    "start_date": "1/20/2015",
    "end_date": "3/20/2015",
    "term_yr": "2015",
    "course_cntl_num": "11111",
    "ldap_uid": null,
    "enrollment_count": "20",
    "cross_listed_ccns": null,
    "co_scheduled_ccns": null
  },
  {
    "term_cd": "B",
    "course_id": "2015-B-87672",
    "course_name": "different_course_name",
    "cross_listed_flag": "Y",
    "course_title_short": "PROB THEORY",
    "dept_name": "STAT",
    "catalog_id": "C205A",
    "instruction_format": "LEC",
    "section_num": "001",
    "primary_secondary_cd": "P",
    "sis_id": "UID:10316",
    "affiliations": "EMPLOYEE-TYPE-ACADEMIC,STUDENT-STATUS-EXPIRED",
    "first_name": "different_first_name",
    "last_name": "different_last_name",
    "email_address": "different_email_address@berkeley.edu",
    "evaluate": null,
    "dept_form": null,
    "evaluation_type": "X",
    "modular_course": "N",
    "start_date": "1/20/2015",
    "end_date": "5/8/2015",
    "term_yr": "2015",
    "course_cntl_num": "87672",
    "ldap_uid": "10316",
    "enrollment_count": "20",
    "cross_listed_ccns": "54432,87672",
    "co_scheduled_ccns": "54432,87672"
  },
  {
    "term_cd": "B",
    "course_id": "2015-B-99999_wrong",
    "course_name": "course_name",
    "cross_listed_flag": null,
    "course_title_short": null,
    "dept_name": "STAT",
    "catalog_id": "999",
    "instruction_format": "LEC",
    "section_num": "001",
    "primary_secondary_cd": "P",
    "sis_id": "UID:bad_data",
    "affiliations": "EMPLOYEE-TYPE-ACADEMIC,STUDENT-STATUS-EXPIRED",
    "first_name": "first_name",
    "last_name": "last_name",
    "email_address": "email_address@berkeley.edu",
    "evaluate": null,
    "dept_form": null,
    "evaluation_type": null,
    "modular_course": "n",
    "start_date": null,
    "end_date": null,
    "term_yr": "2015",
    "course_cntl_num": "99999",
    "ldap_uid": "bad_data",
    "enrollment_count": "20",
    "cross_listed_ccns": null,
    "co_scheduled_ccns": null
  }
]
