<?xml version="1.0"?>
<COMM_MESSAGE_PENDING_RESPONSE type="array" xmlns="http://bcs.is.berkeley.edu">
  <PENDING_MESSAGE>
    <EMPLID>24188949</EMPLID>
    <DESCR>Campus Provided Software</DESCR>
    <LASTUPDDTTM>2015-08-26-16.36.29.000000</LASTUPDDTTM>
    <COMM_CATEGORY>ONCG01</COMM_CATEGORY>
    <COMM_CENTER_DESCR>You may download campus-provided software.</COMM_CENTER_DESCR>
    <URL>
      https://bcs-web-dev-03.is.berkeley.edu:8443/psc/bcsdev//EMPLOYEE/HRMS/c/CCI_COMMUNICATION_CENTER_SS.CCI_COMM_TRANS_FSS.GBL?ucCommTransID=00000000010
    </URL>
  </PENDING_MESSAGE>
  <PENDING_MESSAGE>
    <EMPLID>24188949</EMPLID>
    <DESCR>Electronic Funds Transfer</DESCR>
    <LASTUPDDTTM>2015-09-01-12.37.29.000000</LASTUPDDTTM>
    <COMM_CATEGORY>ONCG01</COMM_CATEGORY>
    <COMM_CENTER_DESCR>Get Funds Fast! Electronic Funds Transfer (EFT)</COMM_CENTER_DESCR>
    <URL>
      https://bcs-web-dev-03.is.berkeley.edu:8443/psc/bcsdev//EMPLOYEE/HRMS/c/CCI_COMMUNICATION_CENTER_SS.CCI_COMM_TRANS_FSS.GBL?ucCommTransID=00000000011
    </URL>
  </PENDING_MESSAGE>
</COMM_MESSAGE_PENDING_RESPONSE>
